LICENSE
MANIFEST.in
README.rst
setup.py
google/__init__.py
google/cloud/__init__.py
google/cloud/proto/__init__.py
google/cloud/proto/spanner/__init__.py
google/cloud/proto/spanner/admin/__init__.py
google/cloud/proto/spanner/admin/instance/__init__.py
google/cloud/proto/spanner/admin/instance/v1/__init__.py
google/cloud/proto/spanner/admin/instance/v1/spanner_instance_admin_pb2.py
google/cloud/proto/spanner/admin/instance/v1/spanner_instance_admin_pb2_grpc.py
proto_google_cloud_spanner_admin_instance_v1.egg-info/PKG-INFO
proto_google_cloud_spanner_admin_instance_v1.egg-info/SOURCES.txt
proto_google_cloud_spanner_admin_instance_v1.egg-info/dependency_links.txt
proto_google_cloud_spanner_admin_instance_v1.egg-info/namespace_packages.txt
proto_google_cloud_spanner_admin_instance_v1.egg-info/requires.txt
proto_google_cloud_spanner_admin_instance_v1.egg-info/top_level.txt